<?xml version="1.0" encoding="UTF-8"?>

<ConceptMap xmlns="http://hl7.org/fhir">
  <id value="ConceptMap-R5-Group-elements-for-R4-Group"/>
  <language value="en"/>
  <text>
    <status value="generated"/><div xmlns="http://www.w3.org/1999/xhtml"><p class="res-header-id"><b>Generated Narrative: ConceptMap ConceptMap-R5-Group-elements-for-R4-Group</b></p><a name="ConceptMap-R5-Group-elements-for-R4-Group"> </a><a name="hcConceptMap-R5-Group-elements-for-R4-Group"> </a><p>Mapping from (not specified) to (not specified)</p><br/><p><b>Group 1 </b>Mapping from <code>http://hl7.org/fhir/StructureDefinition/Group|5.0.0</code> to <code>unspecified code system</code></p><table class="grid"><tr><td><b>Source Code</b></td><td><b>Relationship</b></td><td><b>Target Code</b></td><td><b>Comment</b></td></tr><tr><td>Group</td><td>:(equivalent)</td><td>http://hl7.org/fhir/StructureDefinition/Group#Group</td><td>FHIR R5 Resource `Group` is representable via FHIR R4 Resource `Group`.
Element `Group` is mapped to FHIR R4 element `Group`.</td></tr><tr><td>Group.meta (meta)</td><td>:(equivalent)</td><td>http://hl7.org/fhir/StructureDefinition/Group#Group.meta</td><td>Element `Group.meta` is mapped to FHIR R4 element `Group.meta`.</td></tr><tr><td>Group.implicitRules (implicitRules)</td><td>:(equivalent)</td><td>http://hl7.org/fhir/StructureDefinition/Group#Group.implicitRules</td><td>Element `Group.implicitRules` is mapped to FHIR R4 element `Group.implicitRules`.</td></tr><tr><td>Group.language (language)</td><td>:(equivalent)</td><td>http://hl7.org/fhir/StructureDefinition/Group#Group.language</td><td>Element `Group.language` is mapped to FHIR R4 element `Group.language`.</td></tr><tr><td>Group.text (text)</td><td>:(equivalent)</td><td>http://hl7.org/fhir/StructureDefinition/Group#Group.text</td><td>Element `Group.text` is mapped to FHIR R4 element `Group.text`.</td></tr><tr><td>Group.contained (contained)</td><td>:(equivalent)</td><td>http://hl7.org/fhir/StructureDefinition/Group#Group.contained</td><td>Element `Group.contained` is mapped to FHIR R4 element `Group.contained`.</td></tr><tr><td>Group.identifier (identifier)</td><td>:(equivalent)</td><td>http://hl7.org/fhir/StructureDefinition/Group#Group.identifier</td><td>Element `Group.identifier` is mapped to FHIR R4 element `Group.identifier`.</td></tr><tr><td>Group.active (active)</td><td>:(equivalent)</td><td>http://hl7.org/fhir/StructureDefinition/Group#Group.active</td><td>Element `Group.active` is mapped to FHIR R4 element `Group.active`.</td></tr><tr><td>Group.type (type)</td><td>:(equivalent)</td><td>http://hl7.org/fhir/StructureDefinition/Group#Group.type</td><td>Element `Group.type` is mapped to FHIR R4 element `Group.type`.</td></tr><tr><td>Group.membership (membership)</td><td>:(equivalent)</td><td>http://hl7.org/fhir/StructureDefinition/Group#Group</td><td>Element `Group.membership` is will have a context of Group based on following the parent source element upwards and mapping to `Group`.</td></tr><tr><td>Group.code (code)</td><td>:(equivalent)</td><td>http://hl7.org/fhir/StructureDefinition/Group#Group.code</td><td>Element `Group.code` is mapped to FHIR R4 element `Group.code`.</td></tr><tr><td>Group.name (name)</td><td>:(equivalent)</td><td>http://hl7.org/fhir/StructureDefinition/Group#Group.name</td><td>Element `Group.name` is mapped to FHIR R4 element `Group.name`.</td></tr><tr><td>Group.description (description)</td><td>:(equivalent)</td><td>http://hl7.org/fhir/StructureDefinition/Group#Group</td><td>Element `Group.description` is will have a context of Group based on following the parent source element upwards and mapping to `Group`.</td></tr><tr><td>Group.quantity (quantity)</td><td>:(equivalent)</td><td>http://hl7.org/fhir/StructureDefinition/Group#Group.quantity</td><td>Element `Group.quantity` is mapped to FHIR R4 element `Group.quantity`.</td></tr><tr><td>Group.managingEntity (managingEntity)</td><td>:(equivalent)</td><td>http://hl7.org/fhir/StructureDefinition/Group#Group.managingEntity</td><td>Element `Group.managingEntity` is mapped to FHIR R4 element `Group.managingEntity`.</td></tr><tr><td>Group.characteristic (characteristic)</td><td>:(equivalent)</td><td>http://hl7.org/fhir/StructureDefinition/Group#Group.characteristic</td><td>Element `Group.characteristic` is mapped to FHIR R4 element `Group.characteristic`.</td></tr><tr><td>Group.characteristic.code (code)</td><td>:(equivalent)</td><td>http://hl7.org/fhir/StructureDefinition/Group#Group.characteristic.code</td><td>Element `Group.characteristic.code` is mapped to FHIR R4 element `Group.characteristic.code`.</td></tr><tr><td>Group.characteristic.value[x] (value[x])</td><td>:(equivalent)</td><td>http://hl7.org/fhir/StructureDefinition/Group#Group.characteristic.value[x]</td><td>Note that the target element context `Group.characteristic.value[x]` is a choice-type element and cannot directly hold extensions. The context is moved up to parent element `Group.characteristic`.
Element `Group.characteristic.value[x]` is mapped to FHIR R4 element `Group.characteristic.value[x]`.
Note that the target element context `Group.characteristic.value[x]` is a choice-type element and cannot directly hold extensions. The context is moved up to parent element `Group.characteristic`.</td></tr><tr><td>Group.characteristic.exclude (exclude)</td><td>:(equivalent)</td><td>http://hl7.org/fhir/StructureDefinition/Group#Group.characteristic.exclude</td><td>Element `Group.characteristic.exclude` is mapped to FHIR R4 element `Group.characteristic.exclude`.</td></tr><tr><td>Group.characteristic.period (period)</td><td>:(equivalent)</td><td>http://hl7.org/fhir/StructureDefinition/Group#Group.characteristic.period</td><td>Element `Group.characteristic.period` is mapped to FHIR R4 element `Group.characteristic.period`.</td></tr><tr><td>Group.member (member)</td><td>:(equivalent)</td><td>http://hl7.org/fhir/StructureDefinition/Group#Group.member</td><td>Element `Group.member` is mapped to FHIR R4 element `Group.member`.</td></tr><tr><td>Group.member.entity (entity)</td><td>:(equivalent)</td><td>http://hl7.org/fhir/StructureDefinition/Group#Group.member.entity</td><td>Note that there is an externally-defined extension that has been flagged as the representation of FHIR R5 element `Group.member.entity` with an unmapped Reference type: `http://hl7.org/fhir/StructureDefinition/alternate-reference`.
Element `Group.member.entity` is mapped to FHIR R4 element `Group.member.entity`.</td></tr><tr><td>Group.member.period (period)</td><td>:(equivalent)</td><td>http://hl7.org/fhir/StructureDefinition/Group#Group.member.period</td><td>Element `Group.member.period` is mapped to FHIR R4 element `Group.member.period`.</td></tr><tr><td>Group.member.inactive (inactive)</td><td>:(equivalent)</td><td>http://hl7.org/fhir/StructureDefinition/Group#Group.member.inactive</td><td>Element `Group.member.inactive` is mapped to FHIR R4 element `Group.member.inactive`.</td></tr></table></div>
  </text>
  <extension url="http://hl7.org/fhir/StructureDefinition/structuredefinition-wg">
    <valueCode value="fhir"/>
  </extension>
  <extension url="http://hl7.org/fhir/StructureDefinition/structuredefinition-fmm">
    <valueInteger value="0">
      <extension url="http://hl7.org/fhir/StructureDefinition/structuredefinition-conformance-derivedFrom">
        <valueCanonical value="http://hl7.org/fhir/uv/xver/ImplementationGuide/hl7.fhir.uv.xver-r5.r4"/>
      </extension>
    </valueInteger>
  </extension>
  <extension url="http://hl7.org/fhir/StructureDefinition/structuredefinition-standards-status">
    <valueCode value="trial-use">
      <extension url="http://hl7.org/fhir/StructureDefinition/structuredefinition-conformance-derivedFrom">
        <valueCanonical value="http://hl7.org/fhir/uv/xver/ImplementationGuide/hl7.fhir.uv.xver-r5.r4"/>
      </extension>
    </valueCode>
  </extension>
  <url value="http://hl7.org/fhir/5.0/ConceptMap/ConceptMap-R5-Group-elements-for-R4-Group"/>
  <version value="0.0.1-snapshot-3"/>
  <name value="ConceptMapR5GroupElementsForR4Group"/>
  <title value="Cross-version ConceptMap for FHIR R5 resources in FHIR R4"/>
  <status value="active"/>
  <experimental value="false"/>
  <date value="2026-02-09T22:05:43.9084614-06:00"/>
  <contact>
    <name value="FHIR Infrastructure"/>
    <telecom>
      <system value="url"/>
      <value value="http://www.hl7.org/Special/committees/fiwg"/>
    </telecom>
  </contact>
  <description value="This ConceptMap represents the cross-version mapping of resource FHIR R5 for use in FHIR R4."/>
  <jurisdiction>
    <coding>
      <system value="http://unstats.un.org/unsd/methods/m49/m49.htm"/>
      <code value="001"/>
      <display value="World"/>
    </coding>
  </jurisdiction>
  <group>
    <source value="http://hl7.org/fhir/StructureDefinition/Group"/>
    <sourceVersion value="5.0.0"/>
    <element>
      <code value="Group"/>
      <display value="Group"/>
      <target>
        <code value="http://hl7.org/fhir/StructureDefinition/Group#Group"/>
        <equivalence value="relatedto"/>
        <comment value="FHIR R5 Resource `Group` is representable via FHIR R4 Resource `Group`.&#xA;Element `Group` is mapped to FHIR R4 element `Group`."/>
      </target>
    </element>
    <element>
      <code value="Group.meta"/>
      <display value="meta"/>
      <target>
        <code value="http://hl7.org/fhir/StructureDefinition/Group#Group.meta"/>
        <equivalence value="relatedto"/>
        <comment value="Element `Group.meta` is mapped to FHIR R4 element `Group.meta`."/>
      </target>
    </element>
    <element>
      <code value="Group.implicitRules"/>
      <display value="implicitRules"/>
      <target>
        <code value="http://hl7.org/fhir/StructureDefinition/Group#Group.implicitRules"/>
        <equivalence value="relatedto"/>
        <comment value="Element `Group.implicitRules` is mapped to FHIR R4 element `Group.implicitRules`."/>
      </target>
    </element>
    <element>
      <code value="Group.language"/>
      <display value="language"/>
      <target>
        <code value="http://hl7.org/fhir/StructureDefinition/Group#Group.language"/>
        <equivalence value="relatedto"/>
        <comment value="Element `Group.language` is mapped to FHIR R4 element `Group.language`."/>
      </target>
    </element>
    <element>
      <code value="Group.text"/>
      <display value="text"/>
      <target>
        <code value="http://hl7.org/fhir/StructureDefinition/Group#Group.text"/>
        <equivalence value="relatedto"/>
        <comment value="Element `Group.text` is mapped to FHIR R4 element `Group.text`."/>
      </target>
    </element>
    <element>
      <code value="Group.contained"/>
      <display value="contained"/>
      <target>
        <code value="http://hl7.org/fhir/StructureDefinition/Group#Group.contained"/>
        <equivalence value="relatedto"/>
        <comment value="Element `Group.contained` is mapped to FHIR R4 element `Group.contained`."/>
      </target>
    </element>
    <element>
      <code value="Group.identifier"/>
      <display value="identifier"/>
      <target>
        <code value="http://hl7.org/fhir/StructureDefinition/Group#Group.identifier"/>
        <equivalence value="relatedto"/>
        <comment value="Element `Group.identifier` is mapped to FHIR R4 element `Group.identifier`."/>
      </target>
    </element>
    <element>
      <code value="Group.active"/>
      <display value="active"/>
      <target>
        <code value="http://hl7.org/fhir/StructureDefinition/Group#Group.active"/>
        <equivalence value="relatedto"/>
        <comment value="Element `Group.active` is mapped to FHIR R4 element `Group.active`."/>
      </target>
    </element>
    <element>
      <code value="Group.type"/>
      <display value="type"/>
      <target>
        <code value="http://hl7.org/fhir/StructureDefinition/Group#Group.type"/>
        <equivalence value="relatedto"/>
        <comment value="Element `Group.type` is mapped to FHIR R4 element `Group.type`."/>
      </target>
    </element>
    <element>
      <code value="Group.membership"/>
      <display value="membership"/>
      <target>
        <code value="http://hl7.org/fhir/StructureDefinition/Group#Group"/>
        <equivalence value="relatedto"/>
        <comment value="Element `Group.membership` is will have a context of Group based on following the parent source element upwards and mapping to `Group`."/>
      </target>
    </element>
    <element>
      <code value="Group.code"/>
      <display value="code"/>
      <target>
        <code value="http://hl7.org/fhir/StructureDefinition/Group#Group.code"/>
        <equivalence value="relatedto"/>
        <comment value="Element `Group.code` is mapped to FHIR R4 element `Group.code`."/>
      </target>
    </element>
    <element>
      <code value="Group.name"/>
      <display value="name"/>
      <target>
        <code value="http://hl7.org/fhir/StructureDefinition/Group#Group.name"/>
        <equivalence value="relatedto"/>
        <comment value="Element `Group.name` is mapped to FHIR R4 element `Group.name`."/>
      </target>
    </element>
    <element>
      <code value="Group.description"/>
      <display value="description"/>
      <target>
        <code value="http://hl7.org/fhir/StructureDefinition/Group#Group"/>
        <equivalence value="relatedto"/>
        <comment value="Element `Group.description` is will have a context of Group based on following the parent source element upwards and mapping to `Group`."/>
      </target>
    </element>
    <element>
      <code value="Group.quantity"/>
      <display value="quantity"/>
      <target>
        <code value="http://hl7.org/fhir/StructureDefinition/Group#Group.quantity"/>
        <equivalence value="relatedto"/>
        <comment value="Element `Group.quantity` is mapped to FHIR R4 element `Group.quantity`."/>
      </target>
    </element>
    <element>
      <code value="Group.managingEntity"/>
      <display value="managingEntity"/>
      <target>
        <code value="http://hl7.org/fhir/StructureDefinition/Group#Group.managingEntity"/>
        <equivalence value="relatedto"/>
        <comment value="Element `Group.managingEntity` is mapped to FHIR R4 element `Group.managingEntity`."/>
      </target>
    </element>
    <element>
      <code value="Group.characteristic"/>
      <display value="characteristic"/>
      <target>
        <code value="http://hl7.org/fhir/StructureDefinition/Group#Group.characteristic"/>
        <equivalence value="relatedto"/>
        <comment value="Element `Group.characteristic` is mapped to FHIR R4 element `Group.characteristic`."/>
      </target>
    </element>
    <element>
      <code value="Group.characteristic.code"/>
      <display value="code"/>
      <target>
        <code value="http://hl7.org/fhir/StructureDefinition/Group#Group.characteristic.code"/>
        <equivalence value="relatedto"/>
        <comment value="Element `Group.characteristic.code` is mapped to FHIR R4 element `Group.characteristic.code`."/>
      </target>
    </element>
    <element>
      <code value="Group.characteristic.value[x]"/>
      <display value="value[x]"/>
      <target>
        <code value="http://hl7.org/fhir/StructureDefinition/Group#Group.characteristic.value[x]"/>
        <equivalence value="relatedto"/>
        <comment value="Note that the target element context `Group.characteristic.value[x]` is a choice-type element and cannot directly hold extensions. The context is moved up to parent element `Group.characteristic`.&#xA;Element `Group.characteristic.value[x]` is mapped to FHIR R4 element `Group.characteristic.value[x]`.&#xA;Note that the target element context `Group.characteristic.value[x]` is a choice-type element and cannot directly hold extensions. The context is moved up to parent element `Group.characteristic`."/>
      </target>
    </element>
    <element>
      <code value="Group.characteristic.exclude"/>
      <display value="exclude"/>
      <target>
        <code value="http://hl7.org/fhir/StructureDefinition/Group#Group.characteristic.exclude"/>
        <equivalence value="relatedto"/>
        <comment value="Element `Group.characteristic.exclude` is mapped to FHIR R4 element `Group.characteristic.exclude`."/>
      </target>
    </element>
    <element>
      <code value="Group.characteristic.period"/>
      <display value="period"/>
      <target>
        <code value="http://hl7.org/fhir/StructureDefinition/Group#Group.characteristic.period"/>
        <equivalence value="relatedto"/>
        <comment value="Element `Group.characteristic.period` is mapped to FHIR R4 element `Group.characteristic.period`."/>
      </target>
    </element>
    <element>
      <code value="Group.member"/>
      <display value="member"/>
      <target>
        <code value="http://hl7.org/fhir/StructureDefinition/Group#Group.member"/>
        <equivalence value="relatedto"/>
        <comment value="Element `Group.member` is mapped to FHIR R4 element `Group.member`."/>
      </target>
    </element>
    <element>
      <code value="Group.member.entity"/>
      <display value="entity"/>
      <target>
        <code value="http://hl7.org/fhir/StructureDefinition/Group#Group.member.entity"/>
        <equivalence value="relatedto"/>
        <comment value="Note that there is an externally-defined extension that has been flagged as the representation of FHIR R5 element `Group.member.entity` with an unmapped Reference type: `http://hl7.org/fhir/StructureDefinition/alternate-reference`.&#xA;Element `Group.member.entity` is mapped to FHIR R4 element `Group.member.entity`."/>
      </target>
    </element>
    <element>
      <code value="Group.member.period"/>
      <display value="period"/>
      <target>
        <code value="http://hl7.org/fhir/StructureDefinition/Group#Group.member.period"/>
        <equivalence value="relatedto"/>
        <comment value="Element `Group.member.period` is mapped to FHIR R4 element `Group.member.period`."/>
      </target>
    </element>
    <element>
      <code value="Group.member.inactive"/>
      <display value="inactive"/>
      <target>
        <code value="http://hl7.org/fhir/StructureDefinition/Group#Group.member.inactive"/>
        <equivalence value="relatedto"/>
        <comment value="Element `Group.member.inactive` is mapped to FHIR R4 element `Group.member.inactive`."/>
      </target>
    </element>
  </group>
</ConceptMap>