<?xml version="1.0" encoding="UTF-8"?>

<ValueSet xmlns="http://hl7.org/fhir">
  <id value="R5-v2-0426-for-R4"/>
  <language value="en"/>
  <text>
    <status value="generated"/><div xmlns="http://www.w3.org/1999/xhtml"><p class="res-header-id"><b>Generated Narrative: ValueSet R5-v2-0426-for-R4</b></p><a name="R5-v2-0426-for-R4"> </a><a name="hcR5-v2-0426-for-R4"> </a><p>This value set expansion contains 15 concepts.</p><table class="codes"><tr><td><b>System</b></td><td><b>Version</b></td><td style="white-space:nowrap"><b>Code</b></td><td><b>Display</b></td></tr><tr><td><a name="R5-v2-0426-for-R4-http://terminology.hl7.org/CodeSystem/v2-0426-CRYO"> </a><code>http://terminology.hl7.org/CodeSystem/v2-0426</code></td><td>2.1.0</td><td style="white-space:nowrap">  CRYO</td><td>Cryoprecipitated AHF</td></tr><tr><td><a name="R5-v2-0426-for-R4-http://terminology.hl7.org/CodeSystem/v2-0426-CRYOP"> </a><code>http://terminology.hl7.org/CodeSystem/v2-0426</code></td><td>2.1.0</td><td style="white-space:nowrap">  CRYOP</td><td>Pooled Cryoprecipitate</td></tr><tr><td><a name="R5-v2-0426-for-R4-http://terminology.hl7.org/CodeSystem/v2-0426-FFP"> </a><code>http://terminology.hl7.org/CodeSystem/v2-0426</code></td><td>2.1.0</td><td style="white-space:nowrap">  FFP</td><td>Fresh Frozen Plasma</td></tr><tr><td><a name="R5-v2-0426-for-R4-http://terminology.hl7.org/CodeSystem/v2-0426-FFPTH"> </a><code>http://terminology.hl7.org/CodeSystem/v2-0426</code></td><td>2.1.0</td><td style="white-space:nowrap">  FFPTH</td><td>Fresh Frozen Plasma - Thawed</td></tr><tr><td><a name="R5-v2-0426-for-R4-http://terminology.hl7.org/CodeSystem/v2-0426-PC"> </a><code>http://terminology.hl7.org/CodeSystem/v2-0426</code></td><td>2.1.0</td><td style="white-space:nowrap">  PC</td><td>Packed Cells</td></tr><tr><td><a name="R5-v2-0426-for-R4-http://terminology.hl7.org/CodeSystem/v2-0426-PCA"> </a><code>http://terminology.hl7.org/CodeSystem/v2-0426</code></td><td>2.1.0</td><td style="white-space:nowrap">  PCA</td><td>Autologous Packed Cells</td></tr><tr><td><a name="R5-v2-0426-for-R4-http://terminology.hl7.org/CodeSystem/v2-0426-PCNEO"> </a><code>http://terminology.hl7.org/CodeSystem/v2-0426</code></td><td>2.1.0</td><td style="white-space:nowrap">  PCNEO</td><td>Packed Cells - Neonatal</td></tr><tr><td><a name="R5-v2-0426-for-R4-http://terminology.hl7.org/CodeSystem/v2-0426-PCW"> </a><code>http://terminology.hl7.org/CodeSystem/v2-0426</code></td><td>2.1.0</td><td style="white-space:nowrap">  PCW</td><td>Washed Packed Cells</td></tr><tr><td><a name="R5-v2-0426-for-R4-http://terminology.hl7.org/CodeSystem/v2-0426-PLT"> </a><code>http://terminology.hl7.org/CodeSystem/v2-0426</code></td><td>2.1.0</td><td style="white-space:nowrap">  PLT</td><td>Platelet Concentrate</td></tr><tr><td><a name="R5-v2-0426-for-R4-http://terminology.hl7.org/CodeSystem/v2-0426-PLTNEO"> </a><code>http://terminology.hl7.org/CodeSystem/v2-0426</code></td><td>2.1.0</td><td style="white-space:nowrap">  PLTNEO</td><td>Reduced Volume Platelets</td></tr><tr><td><a name="R5-v2-0426-for-R4-http://terminology.hl7.org/CodeSystem/v2-0426-PLTP"> </a><code>http://terminology.hl7.org/CodeSystem/v2-0426</code></td><td>2.1.0</td><td style="white-space:nowrap">  PLTP</td><td>Pooled Platelets</td></tr><tr><td><a name="R5-v2-0426-for-R4-http://terminology.hl7.org/CodeSystem/v2-0426-PLTPH"> </a><code>http://terminology.hl7.org/CodeSystem/v2-0426</code></td><td>2.1.0</td><td style="white-space:nowrap">  PLTPH</td><td>Platelet Pheresis</td></tr><tr><td><a name="R5-v2-0426-for-R4-http://terminology.hl7.org/CodeSystem/v2-0426-PLTPHLR"> </a><code>http://terminology.hl7.org/CodeSystem/v2-0426</code></td><td>2.1.0</td><td style="white-space:nowrap">  PLTPHLR</td><td>Leukoreduced Platelet Pheresis</td></tr><tr><td><a name="R5-v2-0426-for-R4-http://terminology.hl7.org/CodeSystem/v2-0426-RWB"> </a><code>http://terminology.hl7.org/CodeSystem/v2-0426</code></td><td>2.1.0</td><td style="white-space:nowrap">  RWB</td><td>Reconstituted Whole Blood</td></tr><tr><td><a name="R5-v2-0426-for-R4-http://terminology.hl7.org/CodeSystem/v2-0426-WBA"> </a><code>http://terminology.hl7.org/CodeSystem/v2-0426</code></td><td>2.1.0</td><td style="white-space:nowrap">  WBA</td><td>Autologous Whole Blood</td></tr></table></div>
  </text>
  <extension url="http://hl7.org/fhir/StructureDefinition/structuredefinition-wg">
    <valueCode value="fhir"/>
  </extension>
  <extension url="http://hl7.org/fhir/StructureDefinition/package-source">
    <extension url="packageId">
      <valueId value="hl7.fhir.uv.xver-r5.r4"/>
    </extension>
    <extension url="version">
      <valueString value="0.0.1-snapshot-3"/>
    </extension>
    <extension url="uri">
      <valueUri value="http://hl7.org/fhir/uv/xver/ImplementationGuide/hl7.fhir.uv.xver-r5.r4"/>
    </extension>
  </extension>
  <extension url="http://hl7.org/fhir/StructureDefinition/structuredefinition-fmm">
    <valueInteger value="0">
      <extension url="http://hl7.org/fhir/StructureDefinition/structuredefinition-conformance-derivedFrom">
        <valueCanonical value="http://hl7.org/fhir/uv/xver/ImplementationGuide/hl7.fhir.uv.xver-r5.r4"/>
      </extension>
    </valueInteger>
  </extension>
  <extension url="http://hl7.org/fhir/StructureDefinition/structuredefinition-standards-status">
    <valueCode value="trial-use">
      <extension url="http://hl7.org/fhir/StructureDefinition/structuredefinition-conformance-derivedFrom">
        <valueCanonical value="http://hl7.org/fhir/uv/xver/ImplementationGuide/hl7.fhir.uv.xver-r5.r4"/>
      </extension>
    </valueCode>
  </extension>
  <url value="http://hl7.org/fhir/uv/xver/ValueSet/R5-v2-0426-for-R4"/>
  <version value="0.0.1-snapshot-3"/>
  <name value="R5V20426ForR4"/>
  <title value="Cross-version ValueSet R5.Hl7VSBloodProductCode for use in FHIR R4"/>
  <status value="active"/>
  <experimental value="false"/>
  <date value="2026-02-21T19:36:42.9229177+00:00"/>
  <publisher value="FHIR Infrastructure"/>
  <contact>
    <name value="FHIR Infrastructure"/>
    <telecom>
      <system value="url"/>
      <value value="http://www.hl7.org/Special/committees/fiwg"/>
    </telecom>
  </contact>
  <description value="This cross-version ValueSet represents content from `http://terminology.hl7.org/ValueSet/v2-0426|2.0.0` for use in FHIR R4."/>
  <jurisdiction>
    <coding>
      <system value="http://unstats.un.org/unsd/methods/m49/m49.htm"/>
      <code value="001"/>
      <display value="World"/>
    </coding>
  </jurisdiction>
  <purpose value="This value set is part of the cross-version definitions generated to enable use of the&#xD;&#xA;value set `http://terminology.hl7.org/ValueSet/v2-0426|2.0.0` as defined in FHIR R5&#xD;&#xA;in FHIR R4.&#xD;&#xA;&#xD;&#xA;The source value set is bound to the following FHIR R5 elements:&#xD;&#xA;* &#xD;&#xA;&#xD;&#xA;The following concepts are not included in this cross-version definition because they have valid representations&#xD;&#xA;* _no concepts_&#xD;&#xA;&#xD;&#xA;Following are the generation technical comments:&#xD;&#xA;&#xA;FHIR ValueSet `http://terminology.hl7.org/ValueSet/v2-0426|2.0.0`, defined in FHIR R5 does not have any mapping to FHIR R4"/>
  <compose>
    <include>
      <system value="http://terminology.hl7.org/CodeSystem/v2-0426"/>
      <version value="2.1.0"/>
      <concept>
        <code value="CRYO"/>
        <display value="Cryoprecipitated AHF"/>
      </concept>
      <concept>
        <code value="CRYOP"/>
        <display value="Pooled Cryoprecipitate"/>
      </concept>
      <concept>
        <code value="FFP"/>
        <display value="Fresh Frozen Plasma"/>
      </concept>
      <concept>
        <code value="FFPTH"/>
        <display value="Fresh Frozen Plasma - Thawed"/>
      </concept>
      <concept>
        <code value="PC"/>
        <display value="Packed Cells"/>
      </concept>
      <concept>
        <code value="PCA"/>
        <display value="Autologous Packed Cells"/>
      </concept>
      <concept>
        <code value="PCNEO"/>
        <display value="Packed Cells - Neonatal"/>
      </concept>
      <concept>
        <code value="PCW"/>
        <display value="Washed Packed Cells"/>
      </concept>
      <concept>
        <code value="PLT"/>
        <display value="Platelet Concentrate"/>
      </concept>
      <concept>
        <code value="PLTNEO"/>
        <display value="Reduced Volume Platelets"/>
      </concept>
      <concept>
        <code value="PLTP"/>
        <display value="Pooled Platelets"/>
      </concept>
      <concept>
        <code value="PLTPH"/>
        <display value="Platelet Pheresis"/>
      </concept>
      <concept>
        <code value="PLTPHLR"/>
        <display value="Leukoreduced Platelet Pheresis"/>
      </concept>
      <concept>
        <code value="RWB"/>
        <display value="Reconstituted Whole Blood"/>
      </concept>
      <concept>
        <code value="WBA"/>
        <display value="Autologous Whole Blood"/>
      </concept>
    </include>
  </compose>
  <expansion>
    <timestamp value="2026-02-21T19:36:42.9229177+00:00"/>
    <contains>
      <system value="http://terminology.hl7.org/CodeSystem/v2-0426"/>
      <version value="2.1.0"/>
      <code value="CRYO"/>
      <display value="Cryoprecipitated AHF"/>
    </contains>
    <contains>
      <system value="http://terminology.hl7.org/CodeSystem/v2-0426"/>
      <version value="2.1.0"/>
      <code value="CRYOP"/>
      <display value="Pooled Cryoprecipitate"/>
    </contains>
    <contains>
      <system value="http://terminology.hl7.org/CodeSystem/v2-0426"/>
      <version value="2.1.0"/>
      <code value="FFP"/>
      <display value="Fresh Frozen Plasma"/>
    </contains>
    <contains>
      <system value="http://terminology.hl7.org/CodeSystem/v2-0426"/>
      <version value="2.1.0"/>
      <code value="FFPTH"/>
      <display value="Fresh Frozen Plasma - Thawed"/>
    </contains>
    <contains>
      <system value="http://terminology.hl7.org/CodeSystem/v2-0426"/>
      <version value="2.1.0"/>
      <code value="PC"/>
      <display value="Packed Cells"/>
    </contains>
    <contains>
      <system value="http://terminology.hl7.org/CodeSystem/v2-0426"/>
      <version value="2.1.0"/>
      <code value="PCA"/>
      <display value="Autologous Packed Cells"/>
    </contains>
    <contains>
      <system value="http://terminology.hl7.org/CodeSystem/v2-0426"/>
      <version value="2.1.0"/>
      <code value="PCNEO"/>
      <display value="Packed Cells - Neonatal"/>
    </contains>
    <contains>
      <system value="http://terminology.hl7.org/CodeSystem/v2-0426"/>
      <version value="2.1.0"/>
      <code value="PCW"/>
      <display value="Washed Packed Cells"/>
    </contains>
    <contains>
      <system value="http://terminology.hl7.org/CodeSystem/v2-0426"/>
      <version value="2.1.0"/>
      <code value="PLT"/>
      <display value="Platelet Concentrate"/>
    </contains>
    <contains>
      <system value="http://terminology.hl7.org/CodeSystem/v2-0426"/>
      <version value="2.1.0"/>
      <code value="PLTNEO"/>
      <display value="Reduced Volume Platelets"/>
    </contains>
    <contains>
      <system value="http://terminology.hl7.org/CodeSystem/v2-0426"/>
      <version value="2.1.0"/>
      <code value="PLTP"/>
      <display value="Pooled Platelets"/>
    </contains>
    <contains>
      <system value="http://terminology.hl7.org/CodeSystem/v2-0426"/>
      <version value="2.1.0"/>
      <code value="PLTPH"/>
      <display value="Platelet Pheresis"/>
    </contains>
    <contains>
      <system value="http://terminology.hl7.org/CodeSystem/v2-0426"/>
      <version value="2.1.0"/>
      <code value="PLTPHLR"/>
      <display value="Leukoreduced Platelet Pheresis"/>
    </contains>
    <contains>
      <system value="http://terminology.hl7.org/CodeSystem/v2-0426"/>
      <version value="2.1.0"/>
      <code value="RWB"/>
      <display value="Reconstituted Whole Blood"/>
    </contains>
    <contains>
      <system value="http://terminology.hl7.org/CodeSystem/v2-0426"/>
      <version value="2.1.0"/>
      <code value="WBA"/>
      <display value="Autologous Whole Blood"/>
    </contains>
  </expansion>
</ValueSet>