<?xml version="1.0" encoding="UTF-8"?>

<ConceptMap xmlns="http://hl7.org/fhir">
  <id value="ConceptMap-R5-Person-elements-for-R4-Person"/>
  <text>
    <status value="generated"/><div xmlns="http://www.w3.org/1999/xhtml"><p class="res-header-id"><b>Generated Narrative: ConceptMap ConceptMap-R5-Person-elements-for-R4-Person</b></p><a name="ConceptMap-R5-Person-elements-for-R4-Person"> </a><a name="hcConceptMap-R5-Person-elements-for-R4-Person"> </a><p>Mapping from (not specified) to (not specified)</p><br/><p><b>Group 1 </b>Mapping from <code>http://hl7.org/fhir/StructureDefinition/Person|5.0.0</code> to <code>unspecified code system</code></p><table class="grid"><tr><td><b>Source Code</b></td><td><b>Relationship</b></td><td><b>Target Code</b></td><td><b>Comment</b></td></tr><tr><td>Person</td><td>:(equivalent)</td><td>http://hl7.org/fhir/StructureDefinition/Person#Person</td><td>FHIR R5 Resource `Person` is representable via FHIR R4B Resource `Person`.
Element `Person` is mapped to FHIR R4B element `Person`.</td></tr><tr><td>Person.meta (meta)</td><td>:(equivalent)</td><td>http://hl7.org/fhir/StructureDefinition/Person#Person.meta</td><td>Element `Person.meta` is mapped to FHIR R4B element `Person.meta`.</td></tr><tr><td>Person.implicitRules (implicitRules)</td><td>:(equivalent)</td><td>http://hl7.org/fhir/StructureDefinition/Person#Person.implicitRules</td><td>Element `Person.implicitRules` is mapped to FHIR R4B element `Person.implicitRules`.</td></tr><tr><td>Person.language (language)</td><td>:(equivalent)</td><td>http://hl7.org/fhir/StructureDefinition/Person#Person.language</td><td>Element `Person.language` is mapped to FHIR R4B element `Person.language`.</td></tr><tr><td>Person.text (text)</td><td>:(equivalent)</td><td>http://hl7.org/fhir/StructureDefinition/Person#Person.text</td><td>Element `Person.text` is mapped to FHIR R4B element `Person.text`.</td></tr><tr><td>Person.contained (contained)</td><td>:(equivalent)</td><td>http://hl7.org/fhir/StructureDefinition/Person#Person.contained</td><td>Element `Person.contained` is mapped to FHIR R4B element `Person.contained`.</td></tr><tr><td>Person.identifier (identifier)</td><td>:(equivalent)</td><td>http://hl7.org/fhir/StructureDefinition/Person#Person.identifier</td><td>Element `Person.identifier` is mapped to FHIR R4B element `Person.identifier`.</td></tr><tr><td>Person.active (active)</td><td>:(equivalent)</td><td>http://hl7.org/fhir/StructureDefinition/Person#Person.active</td><td>Element `Person.active` is mapped to FHIR R4B element `Person.active`.</td></tr><tr><td>Person.name (name)</td><td>:(equivalent)</td><td>http://hl7.org/fhir/StructureDefinition/Person#Person.name</td><td>Element `Person.name` is mapped to FHIR R4B element `Person.name`.</td></tr><tr><td>Person.telecom (telecom)</td><td>:(equivalent)</td><td>http://hl7.org/fhir/StructureDefinition/Person#Person.telecom</td><td>Element `Person.telecom` is mapped to FHIR R4B element `Person.telecom`.</td></tr><tr><td>Person.gender (gender)</td><td>:(equivalent)</td><td>http://hl7.org/fhir/StructureDefinition/Person#Person.gender</td><td>Element `Person.gender` is mapped to FHIR R4B element `Person.gender`.</td></tr><tr><td>Person.birthDate (birthDate)</td><td>:(equivalent)</td><td>http://hl7.org/fhir/StructureDefinition/Person#Person.birthDate</td><td>Element `Person.birthDate` is mapped to FHIR R4B element `Person.birthDate`.</td></tr><tr><td>Person.deceased[x] (deceased[x])</td><td>:(equivalent)</td><td>http://hl7.org/fhir/5.0/StructureDefinition/extension-Person.deceased</td><td>Element `Person.deceased[x]` is mapped to FHIR R4B structure `Person`, but has no target element specified.</td></tr><tr><td>Person.address (address)</td><td>:(equivalent)</td><td>http://hl7.org/fhir/StructureDefinition/Person#Person.address</td><td>Element `Person.address` is mapped to FHIR R4B element `Person.address`.</td></tr><tr><td>Person.maritalStatus (maritalStatus)</td><td>:(equivalent)</td><td>http://hl7.org/fhir/5.0/StructureDefinition/extension-Person.maritalStatus</td><td>Element `Person.maritalStatus` is mapped to FHIR R4B structure `Person`, but has no target element specified.</td></tr><tr><td>Person.photo (photo)</td><td>:(equivalent)</td><td>http://hl7.org/fhir/StructureDefinition/Person#Person.photo</td><td>Element `Person.photo` is mapped to FHIR R4B element `Person.photo`.</td></tr><tr><td>Person.communication (communication)</td><td>:(equivalent)</td><td>http://hl7.org/fhir/5.0/StructureDefinition/extension-Person.communication</td><td>Element `Person.communication` is mapped to FHIR R4B structure `Person`, but has no target element specified.</td></tr><tr><td>Person.communication.language (language)</td><td>:(equivalent)</td><td>http://hl7.org/fhir/5.0/StructureDefinition/extension-Person.communication:language</td><td>Element `Person.communication.language` is part of an existing definition because parent element `Person.communication` requires a cross-version extension.
Element `Person.communication.language` is mapped to FHIR R4B structure `Person`, but has no target element specified.</td></tr><tr><td>Person.communication.preferred (preferred)</td><td>:(equivalent)</td><td>http://hl7.org/fhir/5.0/StructureDefinition/extension-Person.communication:preferred</td><td>Element `Person.communication.preferred` is part of an existing definition because parent element `Person.communication` requires a cross-version extension.
Element `Person.communication.preferred` is mapped to FHIR R4B structure `Person`, but has no target element specified.</td></tr><tr><td>Person.managingOrganization (managingOrganization)</td><td>:(equivalent)</td><td>http://hl7.org/fhir/StructureDefinition/Person#Person.managingOrganization</td><td>Element `Person.managingOrganization` is mapped to FHIR R4B element `Person.managingOrganization`.</td></tr><tr><td>Person.link (link)</td><td>:(equivalent)</td><td>http://hl7.org/fhir/StructureDefinition/Person#Person.link</td><td>Element `Person.link` is mapped to FHIR R4B element `Person.link`.</td></tr><tr><td>Person.link.target (target)</td><td>:(equivalent)</td><td>http://hl7.org/fhir/StructureDefinition/Person#Person.link.target</td><td>Element `Person.link.target` is mapped to FHIR R4B element `Person.link.target`.</td></tr><tr><td>Person.link.assurance (assurance)</td><td>:(equivalent)</td><td>http://hl7.org/fhir/StructureDefinition/Person#Person.link.assurance</td><td>Element `Person.link.assurance` is mapped to FHIR R4B element `Person.link.assurance`.</td></tr></table></div>
  </text>
  <extension url="http://hl7.org/fhir/StructureDefinition/structuredefinition-wg">
    <valueCode value="fhir"/>
  </extension>
  <extension url="http://hl7.org/fhir/StructureDefinition/structuredefinition-fmm">
    <valueInteger value="0">
      <extension url="http://hl7.org/fhir/StructureDefinition/structuredefinition-conformance-derivedFrom">
        <valueCanonical value="http://hl7.org/fhir/uv/xver/ImplementationGuide/hl7.fhir.uv.xver-r5.r4"/>
      </extension>
    </valueInteger>
  </extension>
  <extension url="http://hl7.org/fhir/StructureDefinition/structuredefinition-standards-status">
    <valueCode value="trial-use">
      <extension url="http://hl7.org/fhir/StructureDefinition/structuredefinition-conformance-derivedFrom">
        <valueCanonical value="http://hl7.org/fhir/uv/xver/ImplementationGuide/hl7.fhir.uv.xver-r5.r4"/>
      </extension>
    </valueCode>
  </extension>
  <url value="http://hl7.org/fhir/5.0/ConceptMap/ConceptMap-R5-Person-elements-for-R4-Person"/>
  <version value="0.0.1-snapshot-3"/>
  <name value="ConceptMapR5PersonElementsForR4Person"/>
  <title value="Cross-version ConceptMap for FHIR R5 resources in FHIR R4"/>
  <status value="active"/>
  <experimental value="false"/>
  <date value="2026-02-06T13:17:33.9177249-06:00"/>
  <contact>
    <name value="FHIR Infrastructure"/>
    <telecom>
      <system value="url"/>
      <value value="http://www.hl7.org/Special/committees/fiwg"/>
    </telecom>
  </contact>
  <description value="This ConceptMap represents the cross-version mapping of resource FHIR R5 for use in FHIR R4."/>
  <jurisdiction>
    <coding>
      <system value="http://unstats.un.org/unsd/methods/m49/m49.htm"/>
      <code value="001"/>
      <display value="World"/>
    </coding>
  </jurisdiction>
  <group>
    <source value="http://hl7.org/fhir/StructureDefinition/Person"/>
    <sourceVersion value="5.0.0"/>
    <element>
      <code value="Person"/>
      <display value="Person"/>
      <target>
        <code value="http://hl7.org/fhir/StructureDefinition/Person#Person"/>
        <equivalence value="relatedto"/>
        <comment value="FHIR R5 Resource `Person` is representable via FHIR R4B Resource `Person`.&#xA;Element `Person` is mapped to FHIR R4B element `Person`."/>
      </target>
    </element>
    <element>
      <code value="Person.meta"/>
      <display value="meta"/>
      <target>
        <code value="http://hl7.org/fhir/StructureDefinition/Person#Person.meta"/>
        <equivalence value="relatedto"/>
        <comment value="Element `Person.meta` is mapped to FHIR R4B element `Person.meta`."/>
      </target>
    </element>
    <element>
      <code value="Person.implicitRules"/>
      <display value="implicitRules"/>
      <target>
        <code value="http://hl7.org/fhir/StructureDefinition/Person#Person.implicitRules"/>
        <equivalence value="relatedto"/>
        <comment value="Element `Person.implicitRules` is mapped to FHIR R4B element `Person.implicitRules`."/>
      </target>
    </element>
    <element>
      <code value="Person.language"/>
      <display value="language"/>
      <target>
        <code value="http://hl7.org/fhir/StructureDefinition/Person#Person.language"/>
        <equivalence value="relatedto"/>
        <comment value="Element `Person.language` is mapped to FHIR R4B element `Person.language`."/>
      </target>
    </element>
    <element>
      <code value="Person.text"/>
      <display value="text"/>
      <target>
        <code value="http://hl7.org/fhir/StructureDefinition/Person#Person.text"/>
        <equivalence value="relatedto"/>
        <comment value="Element `Person.text` is mapped to FHIR R4B element `Person.text`."/>
      </target>
    </element>
    <element>
      <code value="Person.contained"/>
      <display value="contained"/>
      <target>
        <code value="http://hl7.org/fhir/StructureDefinition/Person#Person.contained"/>
        <equivalence value="relatedto"/>
        <comment value="Element `Person.contained` is mapped to FHIR R4B element `Person.contained`."/>
      </target>
    </element>
    <element>
      <code value="Person.identifier"/>
      <display value="identifier"/>
      <target>
        <code value="http://hl7.org/fhir/StructureDefinition/Person#Person.identifier"/>
        <equivalence value="relatedto"/>
        <comment value="Element `Person.identifier` is mapped to FHIR R4B element `Person.identifier`."/>
      </target>
    </element>
    <element>
      <code value="Person.active"/>
      <display value="active"/>
      <target>
        <code value="http://hl7.org/fhir/StructureDefinition/Person#Person.active"/>
        <equivalence value="relatedto"/>
        <comment value="Element `Person.active` is mapped to FHIR R4B element `Person.active`."/>
      </target>
    </element>
    <element>
      <code value="Person.name"/>
      <display value="name"/>
      <target>
        <code value="http://hl7.org/fhir/StructureDefinition/Person#Person.name"/>
        <equivalence value="relatedto"/>
        <comment value="Element `Person.name` is mapped to FHIR R4B element `Person.name`."/>
      </target>
    </element>
    <element>
      <code value="Person.telecom"/>
      <display value="telecom"/>
      <target>
        <code value="http://hl7.org/fhir/StructureDefinition/Person#Person.telecom"/>
        <equivalence value="relatedto"/>
        <comment value="Element `Person.telecom` is mapped to FHIR R4B element `Person.telecom`."/>
      </target>
    </element>
    <element>
      <code value="Person.gender"/>
      <display value="gender"/>
      <target>
        <code value="http://hl7.org/fhir/StructureDefinition/Person#Person.gender"/>
        <equivalence value="relatedto"/>
        <comment value="Element `Person.gender` is mapped to FHIR R4B element `Person.gender`."/>
      </target>
    </element>
    <element>
      <code value="Person.birthDate"/>
      <display value="birthDate"/>
      <target>
        <code value="http://hl7.org/fhir/StructureDefinition/Person#Person.birthDate"/>
        <equivalence value="relatedto"/>
        <comment value="Element `Person.birthDate` is mapped to FHIR R4B element `Person.birthDate`."/>
      </target>
    </element>
    <element>
      <code value="Person.deceased[x]"/>
      <display value="deceased[x]"/>
      <target>
        <code value="http://hl7.org/fhir/5.0/StructureDefinition/extension-Person.deceased"/>
        <equivalence value="relatedto"/>
        <comment value="Element `Person.deceased[x]` is mapped to FHIR R4B structure `Person`, but has no target element specified."/>
      </target>
    </element>
    <element>
      <code value="Person.address"/>
      <display value="address"/>
      <target>
        <code value="http://hl7.org/fhir/StructureDefinition/Person#Person.address"/>
        <equivalence value="relatedto"/>
        <comment value="Element `Person.address` is mapped to FHIR R4B element `Person.address`."/>
      </target>
    </element>
    <element>
      <code value="Person.maritalStatus"/>
      <display value="maritalStatus"/>
      <target>
        <code value="http://hl7.org/fhir/5.0/StructureDefinition/extension-Person.maritalStatus"/>
        <equivalence value="relatedto"/>
        <comment value="Element `Person.maritalStatus` is mapped to FHIR R4B structure `Person`, but has no target element specified."/>
      </target>
    </element>
    <element>
      <code value="Person.photo"/>
      <display value="photo"/>
      <target>
        <code value="http://hl7.org/fhir/StructureDefinition/Person#Person.photo"/>
        <equivalence value="relatedto"/>
        <comment value="Element `Person.photo` is mapped to FHIR R4B element `Person.photo`."/>
      </target>
    </element>
    <element>
      <code value="Person.communication"/>
      <display value="communication"/>
      <target>
        <code value="http://hl7.org/fhir/5.0/StructureDefinition/extension-Person.communication"/>
        <equivalence value="relatedto"/>
        <comment value="Element `Person.communication` is mapped to FHIR R4B structure `Person`, but has no target element specified."/>
      </target>
    </element>
    <element>
      <code value="Person.communication.language"/>
      <display value="language"/>
      <target>
        <code value="http://hl7.org/fhir/5.0/StructureDefinition/extension-Person.communication:language"/>
        <equivalence value="relatedto"/>
        <comment value="Element `Person.communication.language` is part of an existing definition because parent element `Person.communication` requires a cross-version extension.&#xA;Element `Person.communication.language` is mapped to FHIR R4B structure `Person`, but has no target element specified."/>
      </target>
    </element>
    <element>
      <code value="Person.communication.preferred"/>
      <display value="preferred"/>
      <target>
        <code value="http://hl7.org/fhir/5.0/StructureDefinition/extension-Person.communication:preferred"/>
        <equivalence value="relatedto"/>
        <comment value="Element `Person.communication.preferred` is part of an existing definition because parent element `Person.communication` requires a cross-version extension.&#xA;Element `Person.communication.preferred` is mapped to FHIR R4B structure `Person`, but has no target element specified."/>
      </target>
    </element>
    <element>
      <code value="Person.managingOrganization"/>
      <display value="managingOrganization"/>
      <target>
        <code value="http://hl7.org/fhir/StructureDefinition/Person#Person.managingOrganization"/>
        <equivalence value="relatedto"/>
        <comment value="Element `Person.managingOrganization` is mapped to FHIR R4B element `Person.managingOrganization`."/>
      </target>
    </element>
    <element>
      <code value="Person.link"/>
      <display value="link"/>
      <target>
        <code value="http://hl7.org/fhir/StructureDefinition/Person#Person.link"/>
        <equivalence value="relatedto"/>
        <comment value="Element `Person.link` is mapped to FHIR R4B element `Person.link`."/>
      </target>
    </element>
    <element>
      <code value="Person.link.target"/>
      <display value="target"/>
      <target>
        <code value="http://hl7.org/fhir/StructureDefinition/Person#Person.link.target"/>
        <equivalence value="relatedto"/>
        <comment value="Element `Person.link.target` is mapped to FHIR R4B element `Person.link.target`."/>
      </target>
    </element>
    <element>
      <code value="Person.link.assurance"/>
      <display value="assurance"/>
      <target>
        <code value="http://hl7.org/fhir/StructureDefinition/Person#Person.link.assurance"/>
        <equivalence value="relatedto"/>
        <comment value="Element `Person.link.assurance` is mapped to FHIR R4B element `Person.link.assurance`."/>
      </target>
    </element>
  </group>
</ConceptMap>