<?xml version="1.0" encoding="UTF-8"?>

<ValueSet xmlns="http://hl7.org/fhir">
  <id value="R5-v2-0063-for-R4"/>
  <text>
    <status value="generated"/><div xmlns="http://www.w3.org/1999/xhtml"><p class="res-header-id"><b>Generated Narrative: ValueSet R5-v2-0063-for-R4</b></p><a name="R5-v2-0063-for-R4"> </a><a name="hcR5-v2-0063-for-R4"> </a><p>This value set expansion contains 32 concepts.</p><table class="codes"><tr><td><b>System</b></td><td><b>Version</b></td><td style="white-space:nowrap"><b>Code</b></td><td><b>Display</b></td></tr><tr><td><a name="R5-v2-0063-for-R4-http://terminology.hl7.org/CodeSystem/v2-0063-ASC"> </a><code>http://terminology.hl7.org/CodeSystem/v2-0063</code></td><td>2.1.0</td><td style="white-space:nowrap">  ASC</td><td>Associate</td></tr><tr><td><a name="R5-v2-0063-for-R4-http://terminology.hl7.org/CodeSystem/v2-0063-BRO"> </a><code>http://terminology.hl7.org/CodeSystem/v2-0063</code></td><td>2.1.0</td><td style="white-space:nowrap">  BRO</td><td>Brother</td></tr><tr><td><a name="R5-v2-0063-for-R4-http://terminology.hl7.org/CodeSystem/v2-0063-CGV"> </a><code>http://terminology.hl7.org/CodeSystem/v2-0063</code></td><td>2.1.0</td><td style="white-space:nowrap">  CGV</td><td>Care giver</td></tr><tr><td><a name="R5-v2-0063-for-R4-http://terminology.hl7.org/CodeSystem/v2-0063-CHD"> </a><code>http://terminology.hl7.org/CodeSystem/v2-0063</code></td><td>2.1.0</td><td style="white-space:nowrap">  CHD</td><td>Child</td></tr><tr><td><a name="R5-v2-0063-for-R4-http://terminology.hl7.org/CodeSystem/v2-0063-DEP"> </a><code>http://terminology.hl7.org/CodeSystem/v2-0063</code></td><td>2.1.0</td><td style="white-space:nowrap">  DEP</td><td>Handicapped dependent</td></tr><tr><td><a name="R5-v2-0063-for-R4-http://terminology.hl7.org/CodeSystem/v2-0063-DOM"> </a><code>http://terminology.hl7.org/CodeSystem/v2-0063</code></td><td>2.1.0</td><td style="white-space:nowrap">  DOM</td><td>Life partner</td></tr><tr><td><a name="R5-v2-0063-for-R4-http://terminology.hl7.org/CodeSystem/v2-0063-EMC"> </a><code>http://terminology.hl7.org/CodeSystem/v2-0063</code></td><td>2.1.0</td><td style="white-space:nowrap">  EMC</td><td>Emergency contact</td></tr><tr><td><a name="R5-v2-0063-for-R4-http://terminology.hl7.org/CodeSystem/v2-0063-EME"> </a><code>http://terminology.hl7.org/CodeSystem/v2-0063</code></td><td>2.1.0</td><td style="white-space:nowrap">  EME</td><td>Employee</td></tr><tr><td><a name="R5-v2-0063-for-R4-http://terminology.hl7.org/CodeSystem/v2-0063-EMR"> </a><code>http://terminology.hl7.org/CodeSystem/v2-0063</code></td><td>2.1.0</td><td style="white-space:nowrap">  EMR</td><td>Employer</td></tr><tr><td><a name="R5-v2-0063-for-R4-http://terminology.hl7.org/CodeSystem/v2-0063-EXF"> </a><code>http://terminology.hl7.org/CodeSystem/v2-0063</code></td><td>2.1.0</td><td style="white-space:nowrap">  EXF</td><td>Extended family</td></tr><tr><td><a name="R5-v2-0063-for-R4-http://terminology.hl7.org/CodeSystem/v2-0063-FCH"> </a><code>http://terminology.hl7.org/CodeSystem/v2-0063</code></td><td>2.1.0</td><td style="white-space:nowrap">  FCH</td><td>Foster child</td></tr><tr><td><a name="R5-v2-0063-for-R4-http://terminology.hl7.org/CodeSystem/v2-0063-FND"> </a><code>http://terminology.hl7.org/CodeSystem/v2-0063</code></td><td>2.1.0</td><td style="white-space:nowrap">  FND</td><td>Friend</td></tr><tr><td><a name="R5-v2-0063-for-R4-http://terminology.hl7.org/CodeSystem/v2-0063-FTH"> </a><code>http://terminology.hl7.org/CodeSystem/v2-0063</code></td><td>2.1.0</td><td style="white-space:nowrap">  FTH</td><td>Father</td></tr><tr><td><a name="R5-v2-0063-for-R4-http://terminology.hl7.org/CodeSystem/v2-0063-GCH"> </a><code>http://terminology.hl7.org/CodeSystem/v2-0063</code></td><td>2.1.0</td><td style="white-space:nowrap">  GCH</td><td>Grandchild</td></tr><tr><td><a name="R5-v2-0063-for-R4-http://terminology.hl7.org/CodeSystem/v2-0063-GRD"> </a><code>http://terminology.hl7.org/CodeSystem/v2-0063</code></td><td>2.1.0</td><td style="white-space:nowrap">  GRD</td><td>Guardian</td></tr><tr><td><a name="R5-v2-0063-for-R4-http://terminology.hl7.org/CodeSystem/v2-0063-GRP"> </a><code>http://terminology.hl7.org/CodeSystem/v2-0063</code></td><td>2.1.0</td><td style="white-space:nowrap">  GRP</td><td>Grandparent</td></tr><tr><td><a name="R5-v2-0063-for-R4-http://terminology.hl7.org/CodeSystem/v2-0063-MGR"> </a><code>http://terminology.hl7.org/CodeSystem/v2-0063</code></td><td>2.1.0</td><td style="white-space:nowrap">  MGR</td><td>Manager</td></tr><tr><td><a name="R5-v2-0063-for-R4-http://terminology.hl7.org/CodeSystem/v2-0063-MTH"> </a><code>http://terminology.hl7.org/CodeSystem/v2-0063</code></td><td>2.1.0</td><td style="white-space:nowrap">  MTH</td><td>Mother</td></tr><tr><td><a name="R5-v2-0063-for-R4-http://terminology.hl7.org/CodeSystem/v2-0063-NCH"> </a><code>http://terminology.hl7.org/CodeSystem/v2-0063</code></td><td>2.1.0</td><td style="white-space:nowrap">  NCH</td><td>Natural child</td></tr><tr><td><a name="R5-v2-0063-for-R4-http://terminology.hl7.org/CodeSystem/v2-0063-NON"> </a><code>http://terminology.hl7.org/CodeSystem/v2-0063</code></td><td>2.1.0</td><td style="white-space:nowrap">  NON</td><td>None</td></tr><tr><td><a name="R5-v2-0063-for-R4-http://terminology.hl7.org/CodeSystem/v2-0063-OAD"> </a><code>http://terminology.hl7.org/CodeSystem/v2-0063</code></td><td>2.1.0</td><td style="white-space:nowrap">  OAD</td><td>Other adult</td></tr><tr><td><a name="R5-v2-0063-for-R4-http://terminology.hl7.org/CodeSystem/v2-0063-OTH"> </a><code>http://terminology.hl7.org/CodeSystem/v2-0063</code></td><td>2.1.0</td><td style="white-space:nowrap">  OTH</td><td>Other</td></tr><tr><td><a name="R5-v2-0063-for-R4-http://terminology.hl7.org/CodeSystem/v2-0063-OWN"> </a><code>http://terminology.hl7.org/CodeSystem/v2-0063</code></td><td>2.1.0</td><td style="white-space:nowrap">  OWN</td><td>Owner</td></tr><tr><td><a name="R5-v2-0063-for-R4-http://terminology.hl7.org/CodeSystem/v2-0063-PAR"> </a><code>http://terminology.hl7.org/CodeSystem/v2-0063</code></td><td>2.1.0</td><td style="white-space:nowrap">  PAR</td><td>Parent</td></tr><tr><td><a name="R5-v2-0063-for-R4-http://terminology.hl7.org/CodeSystem/v2-0063-SCH"> </a><code>http://terminology.hl7.org/CodeSystem/v2-0063</code></td><td>2.1.0</td><td style="white-space:nowrap">  SCH</td><td>Stepchild</td></tr><tr><td><a name="R5-v2-0063-for-R4-http://terminology.hl7.org/CodeSystem/v2-0063-SEL"> </a><code>http://terminology.hl7.org/CodeSystem/v2-0063</code></td><td>2.1.0</td><td style="white-space:nowrap">  SEL</td><td>Self</td></tr><tr><td><a name="R5-v2-0063-for-R4-http://terminology.hl7.org/CodeSystem/v2-0063-SIB"> </a><code>http://terminology.hl7.org/CodeSystem/v2-0063</code></td><td>2.1.0</td><td style="white-space:nowrap">  SIB</td><td>Sibling</td></tr><tr><td><a name="R5-v2-0063-for-R4-http://terminology.hl7.org/CodeSystem/v2-0063-SIS"> </a><code>http://terminology.hl7.org/CodeSystem/v2-0063</code></td><td>2.1.0</td><td style="white-space:nowrap">  SIS</td><td>Sister</td></tr><tr><td><a name="R5-v2-0063-for-R4-http://terminology.hl7.org/CodeSystem/v2-0063-SPO"> </a><code>http://terminology.hl7.org/CodeSystem/v2-0063</code></td><td>2.1.0</td><td style="white-space:nowrap">  SPO</td><td>Spouse</td></tr><tr><td><a name="R5-v2-0063-for-R4-http://terminology.hl7.org/CodeSystem/v2-0063-TRA"> </a><code>http://terminology.hl7.org/CodeSystem/v2-0063</code></td><td>2.1.0</td><td style="white-space:nowrap">  TRA</td><td>Trainer</td></tr><tr><td><a name="R5-v2-0063-for-R4-http://terminology.hl7.org/CodeSystem/v2-0063-UNK"> </a><code>http://terminology.hl7.org/CodeSystem/v2-0063</code></td><td>2.1.0</td><td style="white-space:nowrap">  UNK</td><td>Unknown</td></tr><tr><td><a name="R5-v2-0063-for-R4-http://terminology.hl7.org/CodeSystem/v2-0063-WRD"> </a><code>http://terminology.hl7.org/CodeSystem/v2-0063</code></td><td>2.1.0</td><td style="white-space:nowrap">  WRD</td><td>Ward of court</td></tr></table></div>
  </text>
  <extension url="http://hl7.org/fhir/StructureDefinition/structuredefinition-wg">
    <valueCode value="fhir"/>
  </extension>
  <extension url="http://hl7.org/fhir/StructureDefinition/package-source">
    <extension url="packageId">
      <valueId value="hl7.fhir.uv.xver-r5.r4"/>
    </extension>
    <extension url="version">
      <valueString value="0.0.1-snapshot-3"/>
    </extension>
    <extension url="uri">
      <valueUri value="http://hl7.org/fhir/uv/xver/ImplementationGuide/hl7.fhir.uv.xver-r5.r4"/>
    </extension>
  </extension>
  <extension url="http://hl7.org/fhir/StructureDefinition/structuredefinition-fmm">
    <valueInteger value="0">
      <extension url="http://hl7.org/fhir/StructureDefinition/structuredefinition-conformance-derivedFrom">
        <valueCanonical value="http://hl7.org/fhir/uv/xver/ImplementationGuide/hl7.fhir.uv.xver-r5.r4"/>
      </extension>
    </valueInteger>
  </extension>
  <extension url="http://hl7.org/fhir/StructureDefinition/structuredefinition-standards-status">
    <valueCode value="trial-use">
      <extension url="http://hl7.org/fhir/StructureDefinition/structuredefinition-conformance-derivedFrom">
        <valueCanonical value="http://hl7.org/fhir/uv/xver/ImplementationGuide/hl7.fhir.uv.xver-r5.r4"/>
      </extension>
    </valueCode>
  </extension>
  <url value="http://hl7.org/fhir/uv/xver/ValueSet/R5-v2-0063-for-R4"/>
  <version value="0.0.1-snapshot-3"/>
  <name value="R5V20063ForR4"/>
  <title value="Cross-version ValueSet R5.Hl7VSRelationship for use in FHIR R4"/>
  <status value="active"/>
  <experimental value="false"/>
  <date value="2026-02-21T19:36:42.9229177+00:00"/>
  <publisher value="FHIR Infrastructure"/>
  <contact>
    <name value="FHIR Infrastructure"/>
    <telecom>
      <system value="url"/>
      <value value="http://www.hl7.org/Special/committees/fiwg"/>
    </telecom>
  </contact>
  <description value="This cross-version ValueSet represents content from `http://terminology.hl7.org/ValueSet/v2-0063|2.0.0` for use in FHIR R4."/>
  <jurisdiction>
    <coding>
      <system value="http://unstats.un.org/unsd/methods/m49/m49.htm"/>
      <code value="001"/>
      <display value="World"/>
    </coding>
  </jurisdiction>
  <purpose value="This value set is part of the cross-version definitions generated to enable use of the&#xD;&#xA;value set `http://terminology.hl7.org/ValueSet/v2-0063|2.0.0` as defined in FHIR R5&#xD;&#xA;in FHIR R4.&#xD;&#xA;&#xD;&#xA;The source value set is bound to the following FHIR R5 elements:&#xD;&#xA;* &#xD;&#xA;&#xD;&#xA;The following concepts are not included in this cross-version definition because they have valid representations&#xD;&#xA;* _no concepts_&#xD;&#xA;&#xD;&#xA;Following are the generation technical comments:&#xD;&#xA;&#xA;FHIR ValueSet `http://terminology.hl7.org/ValueSet/v2-0063|2.0.0`, defined in FHIR R5 does not have any mapping to FHIR R4"/>
  <compose>
    <include>
      <system value="http://terminology.hl7.org/CodeSystem/v2-0063"/>
      <version value="2.1.0"/>
      <concept>
        <code value="ASC"/>
        <display value="Associate"/>
      </concept>
      <concept>
        <code value="BRO"/>
        <display value="Brother"/>
      </concept>
      <concept>
        <code value="CGV"/>
        <display value="Care giver"/>
      </concept>
      <concept>
        <code value="CHD"/>
        <display value="Child"/>
      </concept>
      <concept>
        <code value="DEP"/>
        <display value="Handicapped dependent"/>
      </concept>
      <concept>
        <code value="DOM"/>
        <display value="Life partner"/>
      </concept>
      <concept>
        <code value="EMC"/>
        <display value="Emergency contact"/>
      </concept>
      <concept>
        <code value="EME"/>
        <display value="Employee"/>
      </concept>
      <concept>
        <code value="EMR"/>
        <display value="Employer"/>
      </concept>
      <concept>
        <code value="EXF"/>
        <display value="Extended family"/>
      </concept>
      <concept>
        <code value="FCH"/>
        <display value="Foster child"/>
      </concept>
      <concept>
        <code value="FND"/>
        <display value="Friend"/>
      </concept>
      <concept>
        <code value="FTH"/>
        <display value="Father"/>
      </concept>
      <concept>
        <code value="GCH"/>
        <display value="Grandchild"/>
      </concept>
      <concept>
        <code value="GRD"/>
        <display value="Guardian"/>
      </concept>
      <concept>
        <code value="GRP"/>
        <display value="Grandparent"/>
      </concept>
      <concept>
        <code value="MGR"/>
        <display value="Manager"/>
      </concept>
      <concept>
        <code value="MTH"/>
        <display value="Mother"/>
      </concept>
      <concept>
        <code value="NCH"/>
        <display value="Natural child"/>
      </concept>
      <concept>
        <code value="NON"/>
        <display value="None"/>
      </concept>
      <concept>
        <code value="OAD"/>
        <display value="Other adult"/>
      </concept>
      <concept>
        <code value="OTH"/>
        <display value="Other"/>
      </concept>
      <concept>
        <code value="OWN"/>
        <display value="Owner"/>
      </concept>
      <concept>
        <code value="PAR"/>
        <display value="Parent"/>
      </concept>
      <concept>
        <code value="SCH"/>
        <display value="Stepchild"/>
      </concept>
      <concept>
        <code value="SEL"/>
        <display value="Self"/>
      </concept>
      <concept>
        <code value="SIB"/>
        <display value="Sibling"/>
      </concept>
      <concept>
        <code value="SIS"/>
        <display value="Sister"/>
      </concept>
      <concept>
        <code value="SPO"/>
        <display value="Spouse"/>
      </concept>
      <concept>
        <code value="TRA"/>
        <display value="Trainer"/>
      </concept>
      <concept>
        <code value="UNK"/>
        <display value="Unknown"/>
      </concept>
      <concept>
        <code value="WRD"/>
        <display value="Ward of court"/>
      </concept>
    </include>
  </compose>
  <expansion>
    <timestamp value="2026-02-21T19:36:42.9229177+00:00"/>
    <contains>
      <system value="http://terminology.hl7.org/CodeSystem/v2-0063"/>
      <version value="2.1.0"/>
      <code value="ASC"/>
      <display value="Associate"/>
    </contains>
    <contains>
      <system value="http://terminology.hl7.org/CodeSystem/v2-0063"/>
      <version value="2.1.0"/>
      <code value="BRO"/>
      <display value="Brother"/>
    </contains>
    <contains>
      <system value="http://terminology.hl7.org/CodeSystem/v2-0063"/>
      <version value="2.1.0"/>
      <code value="CGV"/>
      <display value="Care giver"/>
    </contains>
    <contains>
      <system value="http://terminology.hl7.org/CodeSystem/v2-0063"/>
      <version value="2.1.0"/>
      <code value="CHD"/>
      <display value="Child"/>
    </contains>
    <contains>
      <system value="http://terminology.hl7.org/CodeSystem/v2-0063"/>
      <version value="2.1.0"/>
      <code value="DEP"/>
      <display value="Handicapped dependent"/>
    </contains>
    <contains>
      <system value="http://terminology.hl7.org/CodeSystem/v2-0063"/>
      <version value="2.1.0"/>
      <code value="DOM"/>
      <display value="Life partner"/>
    </contains>
    <contains>
      <system value="http://terminology.hl7.org/CodeSystem/v2-0063"/>
      <version value="2.1.0"/>
      <code value="EMC"/>
      <display value="Emergency contact"/>
    </contains>
    <contains>
      <system value="http://terminology.hl7.org/CodeSystem/v2-0063"/>
      <version value="2.1.0"/>
      <code value="EME"/>
      <display value="Employee"/>
    </contains>
    <contains>
      <system value="http://terminology.hl7.org/CodeSystem/v2-0063"/>
      <version value="2.1.0"/>
      <code value="EMR"/>
      <display value="Employer"/>
    </contains>
    <contains>
      <system value="http://terminology.hl7.org/CodeSystem/v2-0063"/>
      <version value="2.1.0"/>
      <code value="EXF"/>
      <display value="Extended family"/>
    </contains>
    <contains>
      <system value="http://terminology.hl7.org/CodeSystem/v2-0063"/>
      <version value="2.1.0"/>
      <code value="FCH"/>
      <display value="Foster child"/>
    </contains>
    <contains>
      <system value="http://terminology.hl7.org/CodeSystem/v2-0063"/>
      <version value="2.1.0"/>
      <code value="FND"/>
      <display value="Friend"/>
    </contains>
    <contains>
      <system value="http://terminology.hl7.org/CodeSystem/v2-0063"/>
      <version value="2.1.0"/>
      <code value="FTH"/>
      <display value="Father"/>
    </contains>
    <contains>
      <system value="http://terminology.hl7.org/CodeSystem/v2-0063"/>
      <version value="2.1.0"/>
      <code value="GCH"/>
      <display value="Grandchild"/>
    </contains>
    <contains>
      <system value="http://terminology.hl7.org/CodeSystem/v2-0063"/>
      <version value="2.1.0"/>
      <code value="GRD"/>
      <display value="Guardian"/>
    </contains>
    <contains>
      <system value="http://terminology.hl7.org/CodeSystem/v2-0063"/>
      <version value="2.1.0"/>
      <code value="GRP"/>
      <display value="Grandparent"/>
    </contains>
    <contains>
      <system value="http://terminology.hl7.org/CodeSystem/v2-0063"/>
      <version value="2.1.0"/>
      <code value="MGR"/>
      <display value="Manager"/>
    </contains>
    <contains>
      <system value="http://terminology.hl7.org/CodeSystem/v2-0063"/>
      <version value="2.1.0"/>
      <code value="MTH"/>
      <display value="Mother"/>
    </contains>
    <contains>
      <system value="http://terminology.hl7.org/CodeSystem/v2-0063"/>
      <version value="2.1.0"/>
      <code value="NCH"/>
      <display value="Natural child"/>
    </contains>
    <contains>
      <system value="http://terminology.hl7.org/CodeSystem/v2-0063"/>
      <version value="2.1.0"/>
      <code value="NON"/>
      <display value="None"/>
    </contains>
    <contains>
      <system value="http://terminology.hl7.org/CodeSystem/v2-0063"/>
      <version value="2.1.0"/>
      <code value="OAD"/>
      <display value="Other adult"/>
    </contains>
    <contains>
      <system value="http://terminology.hl7.org/CodeSystem/v2-0063"/>
      <version value="2.1.0"/>
      <code value="OTH"/>
      <display value="Other"/>
    </contains>
    <contains>
      <system value="http://terminology.hl7.org/CodeSystem/v2-0063"/>
      <version value="2.1.0"/>
      <code value="OWN"/>
      <display value="Owner"/>
    </contains>
    <contains>
      <system value="http://terminology.hl7.org/CodeSystem/v2-0063"/>
      <version value="2.1.0"/>
      <code value="PAR"/>
      <display value="Parent"/>
    </contains>
    <contains>
      <system value="http://terminology.hl7.org/CodeSystem/v2-0063"/>
      <version value="2.1.0"/>
      <code value="SCH"/>
      <display value="Stepchild"/>
    </contains>
    <contains>
      <system value="http://terminology.hl7.org/CodeSystem/v2-0063"/>
      <version value="2.1.0"/>
      <code value="SEL"/>
      <display value="Self"/>
    </contains>
    <contains>
      <system value="http://terminology.hl7.org/CodeSystem/v2-0063"/>
      <version value="2.1.0"/>
      <code value="SIB"/>
      <display value="Sibling"/>
    </contains>
    <contains>
      <system value="http://terminology.hl7.org/CodeSystem/v2-0063"/>
      <version value="2.1.0"/>
      <code value="SIS"/>
      <display value="Sister"/>
    </contains>
    <contains>
      <system value="http://terminology.hl7.org/CodeSystem/v2-0063"/>
      <version value="2.1.0"/>
      <code value="SPO"/>
      <display value="Spouse"/>
    </contains>
    <contains>
      <system value="http://terminology.hl7.org/CodeSystem/v2-0063"/>
      <version value="2.1.0"/>
      <code value="TRA"/>
      <display value="Trainer"/>
    </contains>
    <contains>
      <system value="http://terminology.hl7.org/CodeSystem/v2-0063"/>
      <version value="2.1.0"/>
      <code value="UNK"/>
      <display value="Unknown"/>
    </contains>
    <contains>
      <system value="http://terminology.hl7.org/CodeSystem/v2-0063"/>
      <version value="2.1.0"/>
      <code value="WRD"/>
      <display value="Ward of court"/>
    </contains>
  </expansion>
</ValueSet>